wheatly/__init__.py
wheatly/cli.py
wheatly/errors.py
wheatly/main.py
wheatly/nlp/parser.py
wheatly/runner/runner.py
wheatly/utils.py
wheatly-0.1.0.dist-info/LICENSE
wheatly-0.1.0.dist-info/METADATA
wheatly-0.1.0.dist-info/WHEEL
wheatly-0.1.0.dist-info/entry_points.txt
wheatly-0.1.0.dist-info/RECORD
