Metadata-Version: 2.1
Name: wheatly
Version: 0.1.0
Summary: A natural language testing tool
Home-page: https://github.com/jfcarter2358/wheatly
Keywords: testing,natural language
Author: John Carter
Author-email: jfcarter2358@gmail.com
Requires-Python: >=3.10,<4.0
Classifier: Programming Language :: Python :: 3
Classifier: Programming Language :: Python :: 3.10
Classifier: Programming Language :: Python :: 3.11
Requires-Dist: aphelper (==0.0.6)
Requires-Dist: cartils (==0.0.8)
Requires-Dist: jsoncparser (==0.0.6)
Requires-Dist: pyyaml (==5.4.1)
Requires-Dist: requests (>=2.29.0,<3.0.0)
Project-URL: Repository, https://github.com/jfcarter2358/wheatly
